sap_toolkit/__init__.py
sap_toolkit/client.py
sap_toolkit/server.py
sap_toolkit/utils.py
sap_toolkit/generated/__init__.py
sap_toolkit/generated/eval_server_pb2.py
sap_toolkit/generated/eval_server_pb2_grpc.py
sap_toolkit-1.0.0.dist-info/LICENSE
sap_toolkit-1.0.0.dist-info/METADATA
sap_toolkit-1.0.0.dist-info/WHEEL
sap_toolkit-1.0.0.dist-info/top_level.txt
sap_toolkit-1.0.0.dist-info/RECORD
