Metadata-Version: 2.1
Name: sap-toolkit
Version: 1.0.0
Summary: Toolkit to benchmark and evaluate streaming perception algorithms
Home-page: https://github.com/karthiksharma98/sap-starterkit/tree/master/sap-toolkit
Author: Kartikeya Sharma
Author-email: ksharma@illinois.edu
License: UNKNOWN
Platform: UNKNOWN
Classifier: Programming Language :: Python :: 3
Classifier: License :: OSI Approved :: MIT License
Classifier: Operating System :: OS Independent
Requires-Python: >=3.8
Requires-Dist: grpcio
Requires-Dist: grpcio-tools
Requires-Dist: pycocotools
